CHANGELOG
LICENSE
MANIFEST.in
README
VERSION
setup.cfg
setup.py
demo/README
demo/__init__.py
demo/development.ini
demo/setup.cfg
demo/setup.py
demo/test.ini
demo/who.ini
demo/ldapauth/__init__.py
demo/ldapauth/websetup.py
demo/ldapauth/config/__init__.py
demo/ldapauth/config/app_cfg.py
demo/ldapauth/config/environment.py
demo/ldapauth/config/middleware.py
demo/ldapauth/controllers/__init__.py
demo/ldapauth/controllers/error.py
demo/ldapauth/controllers/root.py
demo/ldapauth/controllers/template.py
demo/ldapauth/lib/__init__.py
demo/ldapauth/lib/app_globals.py
demo/ldapauth/lib/base.py
demo/ldapauth/lib/helpers.py
demo/ldapauth/model/__init__.py
demo/ldapauth/model/identity.py
demo/ldapauth/public/favicon.ico
demo/ldapauth/public/css/style.css
demo/ldapauth/public/images/error.png
demo/ldapauth/public/images/grad_blue_7x80.png
demo/ldapauth/public/images/header_inner2.png
demo/ldapauth/public/images/info.png
demo/ldapauth/public/images/logo.gif
demo/ldapauth/public/images/logo.png
demo/ldapauth/public/images/ok.png
demo/ldapauth/public/images/star.png
demo/ldapauth/public/images/strype2.png
demo/ldapauth/public/images/tg2_04.gif
demo/ldapauth/public/images/tg_under_the_hood.png
demo/ldapauth/public/images/under_the_hood_blue.png
demo/ldapauth/templates/__init__.py
demo/ldapauth/templates/about.html
demo/ldapauth/templates/debug.html
demo/ldapauth/templates/footer.html
demo/ldapauth/templates/header.html
demo/ldapauth/templates/index.html
demo/ldapauth/templates/login.html
demo/ldapauth/templates/master.html
demo/ldapauth/templates/sidebars.html
demo/ldapauth/tests/__init__.py
demo/ldapauth/tests/test_models.py
demo/ldapauth/tests/functional/__init__.py
demo/ldapauth/tests/functional/test_root.py
docs/Makefile
docs/epydoc.conf
docs/source/Demo.rst
docs/source/Install.rst
docs/source/Using.rst
docs/source/conf.py
docs/source/index.rst
docs/source/img/demo_screenshot_authenticated.png
docs/source/img/demo_screenshot_index.png
repoze/__init__.py
repoze.who.plugins.ldap.egg-info/PKG-INFO
repoze.who.plugins.ldap.egg-info/SOURCES.txt
repoze.who.plugins.ldap.egg-info/dependency_links.txt
repoze.who.plugins.ldap.egg-info/namespace_packages.txt
repoze.who.plugins.ldap.egg-info/not-zip-safe
repoze.who.plugins.ldap.egg-info/requires.txt
repoze.who.plugins.ldap.egg-info/top_level.txt
repoze/who/__init__.py
