Metadata-Version: 1.0
Name: repoze.who.plugins.ldap
Version: 1.0
Summary: LDAP plugin for repoze.who
Home-page: http://code.gustavonarea.net/repoze.who.plugins.ldap/
Author: Gustavo Narea
Author-email: me@gustavonarea.net
License: GNU General Public License v3
Download-URL: https://launchpad.net/repoze.who.plugins.ldap/+download
Keywords: ldap web application server wsgi repoze repoze.who
Platform: UNKNOWN
Classifier: Development Status :: 5 - Production/Stable
Classifier: Intended Audience :: Developers
Classifier: License :: OSI Approved :: GNU General Public License (GPL)
Classifier: Natural Language :: English
Classifier: Operating System :: OS Independent
Classifier: Programming Language :: Python
Classifier: Topic :: Internet :: WWW/HTTP :: WSGI :: Middleware
Classifier: Topic :: System :: Systems Administration :: Authentication/Directory :: LDAP
